{"Iteration": 0, "Steps": 1009999, "Epsilon": 0.80810019, "Episodes": 7, "AverageReturn": -20.142857142857142, "AverageDiscountedReturn": -0.9971501370914592, "TDError^2": 0.0056894514709711075}
{"Iteration": 1, "Steps": 1019999, "Epsilon": 0.80620019, "Episodes": 14, "AverageReturn": -19.8, "AverageDiscountedReturn": -1.1056655294444584, "TDError^2": 0.0024949738290160894}
{"Iteration": 2, "Steps": 1029999, "Epsilon": 0.80430019, "Episodes": 21, "AverageReturn": -19.6, "AverageDiscountedReturn": -0.9890184549596526, "TDError^2": 0.0044851782731711864}
{"Iteration": 3, "Steps": 1039999, "Epsilon": 0.80240019, "Episodes": 28, "AverageReturn": -19.5, "AverageDiscountedReturn": -0.7297611675191946, "TDError^2": 0.006496859714388847}
{"Iteration": 4, "Steps": 1049999, "Epsilon": 0.8005001900000001, "Episodes": 35, "AverageReturn": -19.1, "AverageDiscountedReturn": -0.6735546932076016, "TDError^2": 0.005732061807066202}
{"Iteration": 5, "Steps": 1059999, "Epsilon": 0.79860019, "Episodes": 41, "AverageReturn": -19.6, "AverageDiscountedReturn": -0.6094636290839389, "TDError^2": 0.007329332176595926}
{"Iteration": 6, "Steps": 1069999, "Epsilon": 0.79670019, "Episodes": 48, "AverageReturn": -19.6, "AverageDiscountedReturn": -0.9077709791473874, "TDError^2": 0.008030781522393227}
{"Iteration": 7, "Steps": 1079999, "Epsilon": 0.79480019, "Episodes": 55, "AverageReturn": -20.0, "AverageDiscountedReturn": -1.011551768385223, "TDError^2": 0.008729880675673485}
{"Iteration": 8, "Steps": 1089999, "Epsilon": 0.79290019, "Episodes": 62, "AverageReturn": -19.6, "AverageDiscountedReturn": -0.9324464228381109, "TDError^2": 0.0055647254921495914}
{"Iteration": 9, "Steps": 1099999, "Epsilon": 0.79100019, "Episodes": 69, "AverageReturn": -18.9, "AverageDiscountedReturn": -0.9065549401113954, "TDError^2": 0.005277190823107958}
{"Iteration": 10, "Steps": 1109999, "Epsilon": 0.78910019, "Episodes": 75, "AverageReturn": -19.3, "AverageDiscountedReturn": -0.7588907745958676, "TDError^2": 0.00619619432836771}
{"Iteration": 11, "Steps": 1119999, "Epsilon": 0.7872001900000001, "Episodes": 82, "AverageReturn": -19.3, "AverageDiscountedReturn": -0.8286146714548446, "TDError^2": 0.007956580258905888}
{"Iteration": 12, "Steps": 1129999, "Epsilon": 0.7853001900000001, "Episodes": 89, "AverageReturn": -19.5, "AverageDiscountedReturn": -0.770763343341565, "TDError^2": 0.008504560217261314}
{"Iteration": 13, "Steps": 1139999, "Epsilon": 0.78340019, "Episodes": 95, "AverageReturn": -18.6, "AverageDiscountedReturn": -0.9613102963905421, "TDError^2": 0.006963833700865507}
{"Iteration": 14, "Steps": 1149999, "Epsilon": 0.78150019, "Episodes": 102, "AverageReturn": -19.3, "AverageDiscountedReturn": -0.9610510359137813, "TDError^2": 0.006803110241889954}
{"Iteration": 15, "Steps": 1159999, "Epsilon": 0.77960019, "Episodes": 109, "AverageReturn": -19.2, "AverageDiscountedReturn": -0.9953471723365024, "TDError^2": 0.007730183191597462}
{"Iteration": 16, "Steps": 1169999, "Epsilon": 0.77770019, "Episodes": 116, "AverageReturn": -19.5, "AverageDiscountedReturn": -0.9363458689962336, "TDError^2": 0.006366460118442774}
{"Iteration": 17, "Steps": 1179999, "Epsilon": 0.77580019, "Episodes": 122, "AverageReturn": -19.5, "AverageDiscountedReturn": -0.8929270540144738, "TDError^2": 0.011234696954488754}
{"Iteration": 18, "Steps": 1189999, "Epsilon": 0.77390019, "Episodes": 128, "AverageReturn": -19.3, "AverageDiscountedReturn": -0.867146927955338, "TDError^2": 0.007543496321886778}
{"Iteration": 19, "Steps": 1199999, "Epsilon": 0.77200019, "Episodes": 134, "AverageReturn": -19.3, "AverageDiscountedReturn": -0.900643816678547, "TDError^2": 0.006578786298632622}
{"Iteration": 20, "Steps": 1209999, "Epsilon": 0.77010019, "Episodes": 140, "AverageReturn": -19.6, "AverageDiscountedReturn": -0.9572392894190092, "TDError^2": 0.006985097657889128}
{"Iteration": 21, "Steps": 1219999, "Epsilon": 0.7682001900000001, "Episodes": 147, "AverageReturn": -20.2, "AverageDiscountedReturn": -0.7384903366258223, "TDError^2": 0.004217508248984814}
{"Iteration": 22, "Steps": 1229999, "Epsilon": 0.76630019, "Episodes": 154, "AverageReturn": -19.9, "AverageDiscountedReturn": -0.787304073936326, "TDError^2": 0.00467876298353076}
{"Iteration": 23, "Steps": 1239999, "Epsilon": 0.76440019, "Episodes": 160, "AverageReturn": -18.9, "AverageDiscountedReturn": -0.7915276210750355, "TDError^2": 0.006565948016941547}
{"Iteration": 24, "Steps": 1249999, "Epsilon": 0.76250019, "Episodes": 166, "AverageReturn": -19.0, "AverageDiscountedReturn": -0.6378563321753697, "TDError^2": 0.00820490624755621}
{"Iteration": 25, "Steps": 1259999, "Epsilon": 0.76060019, "Episodes": 173, "AverageReturn": -19.9, "AverageDiscountedReturn": -0.8175998302611249, "TDError^2": 0.006253473926335573}
{"Iteration": 26, "Steps": 1269999, "Epsilon": 0.75870019, "Episodes": 180, "AverageReturn": -19.6, "AverageDiscountedReturn": -0.8522631042761756, "TDError^2": 0.011595985852181911}
{"Iteration": 27, "Steps": 1279999, "Epsilon": 0.75680019, "Episodes": 186, "AverageReturn": -19.2, "AverageDiscountedReturn": -1.049178336724381, "TDError^2": 0.006237092427909374}
{"Iteration": 28, "Steps": 1289999, "Epsilon": 0.75490019, "Episodes": 193, "AverageReturn": -19.3, "AverageDiscountedReturn": -1.024306017322902, "TDError^2": 0.006290916819125414}
{"Iteration": 29, "Steps": 1299999, "Epsilon": 0.7530001900000001, "Episodes": 199, "AverageReturn": -19.6, "AverageDiscountedReturn": -1.0586750010430244, "TDError^2": 0.00799552071839571}
{"Iteration": 30, "Steps": 1309999, "Epsilon": 0.7511001900000001, "Episodes": 205, "AverageReturn": -19.6, "AverageDiscountedReturn": -0.9586521758849681, "TDError^2": 0.007995889522135258}
{"Iteration": 31, "Steps": 1319999, "Epsilon": 0.74920019, "Episodes": 211, "AverageReturn": -18.5, "AverageDiscountedReturn": -0.9341906533032857, "TDError^2": 0.005764274392277002}
{"Iteration": 32, "Steps": 1329999, "Epsilon": 0.74730019, "Episodes": 217, "AverageReturn": -18.7, "AverageDiscountedReturn": -0.9896720030461369, "TDError^2": 0.006423100829124451}
{"Iteration": 33, "Steps": 1339999, "Epsilon": 0.74540019, "Episodes": 223, "AverageReturn": -18.8, "AverageDiscountedReturn": -0.9731600653178776, "TDError^2": 0.00568753108382225}
{"Iteration": 34, "Steps": 1349999, "Epsilon": 0.74350019, "Episodes": 228, "AverageReturn": -18.5, "AverageDiscountedReturn": -0.7113100974698703, "TDError^2": 0.0075927358120679855}
{"Iteration": 35, "Steps": 1359999, "Epsilon": 0.74160019, "Episodes": 234, "AverageReturn": -17.9, "AverageDiscountedReturn": -0.3002232907234884, "TDError^2": 0.006762175355106592}
{"Iteration": 36, "Steps": 1369999, "Epsilon": 0.73970019, "Episodes": 240, "AverageReturn": -18.4, "AverageDiscountedReturn": -0.6546847122455066, "TDError^2": 0.007284143473953009}
{"Iteration": 37, "Steps": 1379999, "Epsilon": 0.73780019, "Episodes": 246, "AverageReturn": -18.8, "AverageDiscountedReturn": -0.8088805643722011, "TDError^2": 0.005779787432402372}
{"Iteration": 38, "Steps": 1389999, "Epsilon": 0.73590019, "Episodes": 252, "AverageReturn": -18.5, "AverageDiscountedReturn": -0.7231506764893922, "TDError^2": 0.008867449127137661}
{"Iteration": 39, "Steps": 1399999, "Epsilon": 0.7340001899999999, "Episodes": 258, "AverageReturn": -18.2, "AverageDiscountedReturn": -0.5885773670422474, "TDError^2": 0.009528573602437973}
{"Iteration": 40, "Steps": 1409999, "Epsilon": 0.7321001899999999, "Episodes": 264, "AverageReturn": -18.9, "AverageDiscountedReturn": -0.564744393397991, "TDError^2": 0.009128307923674583}
{"Iteration": 41, "Steps": 1419999, "Epsilon": 0.7302001899999999, "Episodes": 270, "AverageReturn": -19.0, "AverageDiscountedReturn": -0.7927779296308107, "TDError^2": 0.008749178610742092}
{"Iteration": 42, "Steps": 1429999, "Epsilon": 0.72830019, "Episodes": 275, "AverageReturn": -18.5, "AverageDiscountedReturn": -0.6792586571448733, "TDError^2": 0.008567734621465206}
{"Iteration": 43, "Steps": 1439999, "Epsilon": 0.7264001900000001, "Episodes": 281, "AverageReturn": -18.8, "AverageDiscountedReturn": -0.7810271875351391, "TDError^2": 0.00863761454820633}
{"Iteration": 44, "Steps": 1449999, "Epsilon": 0.7245001900000001, "Episodes": 286, "AverageReturn": -18.9, "AverageDiscountedReturn": -0.7683638237257256, "TDError^2": 0.007559393532574177}
{"Iteration": 45, "Steps": 1459999, "Epsilon": 0.7226001900000001, "Episodes": 292, "AverageReturn": -18.2, "AverageDiscountedReturn": -0.8023152444928353, "TDError^2": 0.005871575325727463}
{"Iteration": 46, "Steps": 1469999, "Epsilon": 0.7207001900000001, "Episodes": 297, "AverageReturn": -18.1, "AverageDiscountedReturn": -0.893908840586446, "TDError^2": 0.00570609699934721}
{"Iteration": 47, "Steps": 1479999, "Epsilon": 0.7188001900000001, "Episodes": 302, "AverageReturn": -18.1, "AverageDiscountedReturn": -0.835398152055127, "TDError^2": 0.006211035419255495}
{"Iteration": 48, "Steps": 1489999, "Epsilon": 0.71690019, "Episodes": 308, "AverageReturn": -18.6, "AverageDiscountedReturn": -0.8855300274460329, "TDError^2": 0.00608830526471138}
{"Iteration": 49, "Steps": 1499999, "Epsilon": 0.71500019, "Episodes": 314, "AverageReturn": -19.2, "AverageDiscountedReturn": -0.9154490375810408, "TDError^2": 0.008966697379946709}
{"Iteration": 50, "Steps": 1509999, "Epsilon": 0.71310019, "Episodes": 320, "AverageReturn": -18.8, "AverageDiscountedReturn": -0.7770567732380578, "TDError^2": 0.007521779742091894}
{"Iteration": 51, "Steps": 1519999, "Epsilon": 0.71120019, "Episodes": 325, "AverageReturn": -18.4, "AverageDiscountedReturn": -0.6309030567713222, "TDError^2": 0.0086086206138134}
{"Iteration": 52, "Steps": 1529999, "Epsilon": 0.70930019, "Episodes": 331, "AverageReturn": -19.2, "AverageDiscountedReturn": -0.6650063184149703, "TDError^2": 0.005995558109134436}
{"Iteration": 53, "Steps": 1539999, "Epsilon": 0.70740019, "Episodes": 338, "AverageReturn": -19.0, "AverageDiscountedReturn": -0.719247196374474, "TDError^2": 0.007268344052135944}
{"Iteration": 54, "Steps": 1549999, "Epsilon": 0.70550019, "Episodes": 343, "AverageReturn": -18.9, "AverageDiscountedReturn": -0.7758688337901355, "TDError^2": 0.007463386282324791}
{"Iteration": 55, "Steps": 1559999, "Epsilon": 0.70360019, "Episodes": 349, "AverageReturn": -18.6, "AverageDiscountedReturn": -0.8581860899764207, "TDError^2": 0.0061368076130747795}
{"Iteration": 56, "Steps": 1569999, "Epsilon": 0.70170019, "Episodes": 355, "AverageReturn": -18.3, "AverageDiscountedReturn": -0.6817164560559001, "TDError^2": 0.006308280397206545}
{"Iteration": 57, "Steps": 1579999, "Epsilon": 0.69980019, "Episodes": 360, "AverageReturn": -18.8, "AverageDiscountedReturn": -0.7287119285342135, "TDError^2": 0.006034278776496649}
{"Iteration": 58, "Steps": 1589999, "Epsilon": 0.69790019, "Episodes": 366, "AverageReturn": -18.4, "AverageDiscountedReturn": -0.9022180331847037, "TDError^2": 0.007896616123616695}
{"Iteration": 59, "Steps": 1599999, "Epsilon": 0.69600019, "Episodes": 373, "AverageReturn": -18.5, "AverageDiscountedReturn": -0.8700502497871107, "TDError^2": 0.00523179629817605}
{"Iteration": 60, "Steps": 1609999, "Epsilon": 0.69410019, "Episodes": 378, "AverageReturn": -18.8, "AverageDiscountedReturn": -0.7598713844173913, "TDError^2": 0.0063168806955218315}
{"Iteration": 61, "Steps": 1619999, "Epsilon": 0.69220019, "Episodes": 384, "AverageReturn": -19.0, "AverageDiscountedReturn": -0.6711784010812832, "TDError^2": 0.005628723651170731}
{"Iteration": 62, "Steps": 1629999, "Epsilon": 0.6903001900000001, "Episodes": 389, "AverageReturn": -18.5, "AverageDiscountedReturn": -0.6951660148118645, "TDError^2": 0.00859055295586586}
{"Iteration": 63, "Steps": 1639999, "Epsilon": 0.6884001900000001, "Episodes": 395, "AverageReturn": -19.0, "AverageDiscountedReturn": -0.8611631261072352, "TDError^2": 0.0075234416872262955}
{"Iteration": 64, "Steps": 1649999, "Epsilon": 0.6865001900000001, "Episodes": 401, "AverageReturn": -19.2, "AverageDiscountedReturn": -0.8773804086552396, "TDError^2": 0.008346717804670334}
{"Iteration": 65, "Steps": 1659999, "Epsilon": 0.68460019, "Episodes": 407, "AverageReturn": -18.3, "AverageDiscountedReturn": -0.795140244033792, "TDError^2": 0.008694076910614967}
{"Iteration": 66, "Steps": 1669999, "Epsilon": 0.68270019, "Episodes": 413, "AverageReturn": -17.9, "AverageDiscountedReturn": -0.7504258636854482, "TDError^2": 0.008326737210154533}
{"Iteration": 67, "Steps": 1679999, "Epsilon": 0.68080019, "Episodes": 419, "AverageReturn": -18.2, "AverageDiscountedReturn": -0.7803993991335733, "TDError^2": 0.008577469736337662}
{"Iteration": 68, "Steps": 1689999, "Epsilon": 0.67890019, "Episodes": 425, "AverageReturn": -18.2, "AverageDiscountedReturn": -0.7728215863025518, "TDError^2": 0.006280806846916676}
{"Iteration": 69, "Steps": 1699999, "Epsilon": 0.67700019, "Episodes": 430, "AverageReturn": -19.0, "AverageDiscountedReturn": -0.6873148188889753, "TDError^2": 0.006261584814637899}
{"Iteration": 70, "Steps": 1709999, "Epsilon": 0.67510019, "Episodes": 436, "AverageReturn": -18.5, "AverageDiscountedReturn": -0.6839140549544848, "TDError^2": 0.0056939213536679745}
{"Iteration": 71, "Steps": 1719999, "Epsilon": 0.67320019, "Episodes": 441, "AverageReturn": -18.3, "AverageDiscountedReturn": -0.76289473493628, "TDError^2": 0.008387124165892601}
{"Iteration": 72, "Steps": 1729999, "Epsilon": 0.67130019, "Episodes": 447, "AverageReturn": -17.9, "AverageDiscountedReturn": -0.8023291844841639, "TDError^2": 0.009314670227468014}
{"Iteration": 73, "Steps": 1739999, "Epsilon": 0.66940019, "Episodes": 453, "AverageReturn": -18.4, "AverageDiscountedReturn": -0.9149903331980449, "TDError^2": 0.006381310056895018}
{"Iteration": 74, "Steps": 1749999, "Epsilon": 0.6675001899999999, "Episodes": 459, "AverageReturn": -19.2, "AverageDiscountedReturn": -0.8885198219308504, "TDError^2": 0.008779707364737988}
{"Iteration": 75, "Steps": 1759999, "Epsilon": 0.66560019, "Episodes": 465, "AverageReturn": -18.3, "AverageDiscountedReturn": -0.7641181918011007, "TDError^2": 0.010441768914461136}
{"Iteration": 76, "Steps": 1769999, "Epsilon": 0.66370019, "Episodes": 470, "AverageReturn": -18.2, "AverageDiscountedReturn": -0.6076279115003625, "TDError^2": 0.0060374061577022076}
{"Iteration": 77, "Steps": 1779999, "Epsilon": 0.66180019, "Episodes": 476, "AverageReturn": -18.9, "AverageDiscountedReturn": -0.6824714327636311, "TDError^2": 0.007104125805199146}
{"Iteration": 78, "Steps": 1789999, "Epsilon": 0.6599001900000001, "Episodes": 481, "AverageReturn": -18.5, "AverageDiscountedReturn": -0.7783748975033544, "TDError^2": 0.0077175418846309185}
{"Iteration": 79, "Steps": 1799999, "Epsilon": 0.6580001900000001, "Episodes": 487, "AverageReturn": -18.8, "AverageDiscountedReturn": -0.6868758087407812, "TDError^2": 0.007439591456204653}
{"Iteration": 80, "Steps": 1809999, "Epsilon": 0.6561001900000001, "Episodes": 493, "AverageReturn": -18.4, "AverageDiscountedReturn": -0.8310245720137942, "TDError^2": 0.006387465633451939}
{"Iteration": 81, "Steps": 1819999, "Epsilon": 0.6542001900000001, "Episodes": 497, "AverageReturn": -18.7, "AverageDiscountedReturn": -0.8015110073893453, "TDError^2": 0.008572064340114594}
{"Iteration": 82, "Steps": 1829999, "Epsilon": 0.6523001900000001, "Episodes": 502, "AverageReturn": -17.8, "AverageDiscountedReturn": -0.6431748553557601, "TDError^2": 0.0075721656903624535}
{"Iteration": 83, "Steps": 1839999, "Epsilon": 0.65040019, "Episodes": 507, "AverageReturn": -17.8, "AverageDiscountedReturn": -0.6220365927025981, "TDError^2": 0.009028758853673935}
